triangle_multiplicative_module/__init__.py
triangle_multiplicative_module/triangle_multiplicative_module.py
triangle_multiplicative_module-0.0.3.dist-info/LICENSE
triangle_multiplicative_module-0.0.3.dist-info/METADATA
triangle_multiplicative_module-0.0.3.dist-info/WHEEL
triangle_multiplicative_module-0.0.3.dist-info/top_level.txt
triangle_multiplicative_module-0.0.3.dist-info/RECORD
